django_speedbar-0.2.2.dist-info/DESCRIPTION.rst
django_speedbar-0.2.2.dist-info/METADATA
django_speedbar-0.2.2.dist-info/RECORD
django_speedbar-0.2.2.dist-info/WHEEL
django_speedbar-0.2.2.dist-info/metadata.json
django_speedbar-0.2.2.dist-info/top_level.txt
speedbar/__init__.py
speedbar/middleware.py
speedbar/models.py
speedbar/signals.py
speedbar/urls.py
speedbar/utils.py
speedbar/views.py
speedbar/modules/__init__.py
speedbar/modules/base.py
speedbar/modules/cassandra.py
speedbar/modules/celeryjobs.py
speedbar/modules/haystack.py
speedbar/modules/hostinformation.py
speedbar/modules/memcache.py
speedbar/modules/monkey_patching.py
speedbar/modules/pagetimer.py
speedbar/modules/redis.py
speedbar/modules/requeststages.py
speedbar/modules/sql.py
speedbar/modules/stacktracer.py
speedbar/modules/templates.py
speedbar/templatetags/__init__.py
speedbar/templatetags/speedbar.py
