Metadata-Version: 2.0
Name: django-speedbar
Version: 0.2.2
Summary: Provides a break down of page loading time
Home-page: http://github.com/mixcloud/django-speedbar
Author: Mat Clayton
Author-email: mat@mixcloud.com
License: MIT License
Platform: UNKNOWN
Classifier: Environment :: Web Environment
Classifier: Framework :: Django
Classifier: Intended Audience :: Developers
Classifier: License :: OSI Approved :: MIT License
Classifier: Operating System :: OS Independent
Classifier: Programming Language :: Python
Classifier: Programming Language :: Python :: 2
Classifier: Programming Language :: Python :: 2.7
Classifier: Topic :: Internet :: WWW/HTTP
Classifier: Topic :: Internet :: WWW/HTTP :: Dynamic Content
Requires-Dist: ProxyTypes (>=0.9)
Provides-Extra: test
Requires-Dist: Django (>=1.4,<1.9); extra == 'test'
